UsefulDecorator/NotNone.py
UsefulDecorator/__init__.py
UsefulDecorator-0.0.1a0.dist-info/METADATA
UsefulDecorator-0.0.1a0.dist-info/WHEEL
UsefulDecorator-0.0.1a0.dist-info/top_level.txt
UsefulDecorator-0.0.1a0.dist-info/RECORD
