Metadata-Version: 2.1
Name: UsefulDecorator
Version: 0.0.1.Alpha
Summary: useful decorator
Home-page: UNKNOWN
Author: EGGnmad
Author-email: viewnono1219@gmail.com
License: UNKNOWN
Keywords: decorator
Platform: UNKNOWN
